quickcpp/main.py
quickcpp-0.1.1.dist-info/entry_points.txt
quickcpp-0.1.1.dist-info/LICENSE
quickcpp-0.1.1.dist-info/WHEEL
quickcpp-0.1.1.dist-info/METADATA
quickcpp-0.1.1.dist-info/RECORD
